poe_research_cli/__init__.py
poe_research_cli/__main__.py
poe_research_cli/cli.py
poe_research_cli/client.py
poe_research_cli/state.py
poe_research_cli-0.1.1.dist-info/METADATA
poe_research_cli-0.1.1.dist-info/WHEEL
poe_research_cli-0.1.1.dist-info/entry_points.txt
poe_research_cli-0.1.1.dist-info/RECORD
