Metadata-Version: 2.4
Name: poe-research-cli
Version: 0.1.1
Summary: CLI for Poe Deep Research with retry/resume support
Requires-Python: >=3.10
Requires-Dist: click>=8.0
Requires-Dist: openai>=1.0
Requires-Dist: requests>=2.25
